lupro_scheduler/Asyncio.py
lupro_scheduler/Communication.py
lupro_scheduler/Process.py
lupro_scheduler/Scheduler.py
lupro_scheduler/Thread.py
lupro_scheduler/__init__.py
lupro_scheduler/__version__.py
lupro_scheduler/publictool.py
lupro_scheduler/typing.py
lupro_scheduler-1.0.0.dist-info/LICENSE
lupro_scheduler-1.0.0.dist-info/METADATA
lupro_scheduler-1.0.0.dist-info/WHEEL
lupro_scheduler-1.0.0.dist-info/top_level.txt
lupro_scheduler-1.0.0.dist-info/RECORD
