Metadata-Version: 2.1
Name: lupro-scheduler
Version: 1.0.0
Summary: Lupro Scheduler is a synchronous task chain scheduler support sweeper, multi-thread, multi-process synchronous communication.
Home-page: https://github.com/luxuncang/lupro_scheduler
Author: ShengXin Lu
Author-email: luxuncang@qq.com
License: MIT
Platform: all
Classifier: Intended Audience :: Developers
Classifier: Operating System :: OS Independent
Classifier: Natural Language :: Chinese (Simplified)
Classifier: Programming Language :: Python :: 3.6
Classifier: Programming Language :: Python :: 3.7
Classifier: Programming Language :: Python :: 3.8
Classifier: Programming Language :: Python :: 3.9
Classifier: Programming Language :: Python :: 3.10
Classifier: Topic :: Software Development :: Libraries
License-File: LICENSE
Requires-Dist: gevent
